structlog_journald/__init__.py
structlog_journald/consts.py
structlog_journald/detect.py
structlog_journald/processors.py
structlog_journald/py.typed
structlog_journald-0.5.0.dist-info/METADATA
structlog_journald-0.5.0.dist-info/WHEEL
structlog_journald-0.5.0.dist-info/RECORD
