Metadata-Version: 2.4
Name: structlog-journald
Version: 0.5.0
Summary: Structlog processor to send logs to journald
Project-URL: Homepage, https://github.com/hongquan/structlog-journald
Project-URL: Repository, https://github.com/hongquan/structlog-journald
Project-URL: Documentation, https://structlog-journald.readthedocs.io
Project-URL: Changelog, https://github.com/hongquan/structlog-journald/blob/main/CHANGELOG.md
Author-email: Nguyễn Hồng Quân <ng.hong.quan@gmail.com>
License-Expression: Apache-2.0
Keywords: journald,logging,structlog,systemd
Classifier: Development Status :: 4 - Beta
Classifier: Intended Audience :: Developers
Classifier: License :: OSI Approved :: Apache Software License
Classifier: Programming Language :: Python
Classifier: Programming Language :: Python :: 3
Classifier: Programming Language :: Python :: 3.12
Classifier: Programming Language :: Python :: 3.13
Classifier: Topic :: Software Development :: Libraries :: Python Modules
Requires-Python: >=3.12
Requires-Dist: structlog>=25.1.0
Provides-Extra: cpython
Requires-Dist: systemd-python>=235; extra == 'cpython'
Provides-Extra: cython
Requires-Dist: cysystemd>=2.0.1; extra == 'cython'
